genops/__init__.py
genops/client.py
genops-0.8.1.dist-info/LICENSE
genops-0.8.1.dist-info/METADATA
genops-0.8.1.dist-info/WHEEL
genops-0.8.1.dist-info/top_level.txt
genops-0.8.1.dist-info/RECORD
